mcp_network_tester.py
mcp_network_tester-0.1.0.dist-info/licenses/LICENSE
mcp_network_tester-0.1.0.dist-info/METADATA
mcp_network_tester-0.1.0.dist-info/WHEEL
mcp_network_tester-0.1.0.dist-info/entry_points.txt
mcp_network_tester-0.1.0.dist-info/top_level.txt
mcp_network_tester-0.1.0.dist-info/RECORD
