Metadata-Version: 2.4
Name: mcp-network-tester
Version: 0.1.0
Summary: MCP server providing TCP connectivity checks, DNS resolve, and system ping
Author: Yucen
License: MIT
Project-URL: Repository, https://gitee.com/lyc067/Isitconnect
Keywords: MCP,Model Context Protocol,network,ping,tcp,dns
Classifier: Programming Language :: Python :: 3
Classifier: License :: OSI Approved :: MIT License
Classifier: Operating System :: OS Independent
Requires-Python: >=3.9
License-File: LICENSE
Requires-Dist: mcp>=1.0.0
Dynamic: license-file
